benchmark/__init__.py
benchmark/log.py
benchmark/util.py
pyagentic/__init__.py
pyagentic/telemetry.py
pyagentic/util.py
script/__init__.py
test/__init__.py
PyAgentic-0.0.2.dist-info/LICENSE
PyAgentic-0.0.2.dist-info/METADATA
PyAgentic-0.0.2.dist-info/WHEEL
PyAgentic-0.0.2.dist-info/top_level.txt
PyAgentic-0.0.2.dist-info/RECORD
